{
  "formatVersion": 1,
  "database": {
    "version": 1,
    "identityHash": "456585c3c36311ca0bbd2befce31492b",
    "entities": [
      {
        "tableName": "movie_detail",
        "createSql": "CREATE TABLE IF NOT EXISTS `${TABLE_NAME}` (`movie_id` INTEGER NOT NULL, `title` TEXT NOT NULL, `overview` TEXT, `release_year` TEXT NOT NULL, `poster_path` TEXT NOT NULL, PRIMARY KEY(`movie_id`))",
        "fields": [
          {
            "fieldPath": "id",
            "columnName": "movie_id",
            "affinity": "INTEGER",
            "notNull": true
          },
          {
            "fieldPath": "title",
            "columnName": "title",
            "affinity": "TEXT",
            "notNull": true
          },
          {
            "fieldPath": "overview",
            "columnName": "overview",
            "affinity": "TEXT",
            "notNull": false
          },
          {
            "fieldPath": "releaseYear",
            "columnName": "release_year",
            "affinity": "TEXT",
            "notNull": true
          },
          {
            "fieldPath": "posterPath",
            "columnName": "poster_path",
            "affinity": "TEXT",
            "notNull": true
          }
        ],
        "primaryKey": {
          "columnNames": [
            "movie_id"
          ],
          "autoGenerate": false
        },
        "indices": [],
        "foreignKeys": []
      }
    ],
    "views": [],
    "setupQueries": [
      "CREATE TABLE IF NOT EXISTS room_master_table (id INTEGER PRIMARY KEY,identity_hash TEXT)",
      "INSERT OR REPLACE INTO room_master_table (id,identity_hash) VALUES(42, '456585c3c36311ca0bbd2befce31492b')"
    ]
  }
}